{
  "sorted_middleware": [],
  "middleware": {
    "/": {
      "files": [
        "server/edge/chunks/_70dfdf7b._.js",
        "server/edge/chunks/[root of the server]__fb7dcd71._.js",
        "server/edge/chunks/edge-wrapper_53713179.js"
      ],
      "name": "middleware",
      "page": "/",
      "matchers": [
        {
          "regexp": "/:nextData(_next/data/[^/]{1,})?/api/admin/list{(\\\\.json)}?",
          "originalSource": "/api/admin/list"
        },
        {
          "regexp": "/:nextData(_next/data/[^/]{1,})?/api/admin/auth/verify{(\\\\.json)}?",
          "originalSource": "/api/admin/auth/verify"
        },
        {
          "regexp": "/:nextData(_next/data/[^/]{1,})?/api/dropshipper/list{(\\\\.json)}?",
          "originalSource": "/api/dropshipper/list"
        },
        {
          "regexp": "/:nextData(_next/data/[^/]{1,})?/api/dropshipper/auth/verify{(\\\\.json)}?",
          "originalSource": "/api/dropshipper/auth/verify"
        },
        {
          "regexp": "/:nextData(_next/data/[^/]{1,})?/api/supplier/list{(\\\\.json)}?",
          "originalSource": "/api/supplier/list"
        },
        {
          "regexp": "/:nextData(_next/data/[^/]{1,})?/api/supplier/auth/verify{(\\\\.json)}?",
          "originalSource": "/api/supplier/auth/verify"
        },
        {
          "regexp": "/:nextData(_next/data/[^/]{1,})?/api/product/create{(\\\\.json)}?",
          "originalSource": "/api/product/create"
        },
        {
          "regexp": "/:nextData(_next/data/[^/]{1,})?/api/category{(\\\\.json)}?",
          "originalSource": "/api/category"
        },
        {
          "regexp": "/:nextData(_next/data/[^/]{1,})?/api/category/:path*{(\\\\.json)}?",
          "originalSource": "/api/category/:path*"
        },
        {
          "regexp": "/:nextData(_next/data/[^/]{1,})?/api/brand{(\\\\.json)}?",
          "originalSource": "/api/brand"
        },
        {
          "regexp": "/:nextData(_next/data/[^/]{1,})?/api/brand/:path*{(\\\\.json)}?",
          "originalSource": "/api/brand/:path*"
        }
      ],
      "wasm": [],
      "assets": [],
      "env": {
        "__NEXT_BUILD_ID": "development",
        "NEXT_SERVER_ACTIONS_ENCRYPTION_KEY": "HsF2tAf05pWk1bxl5T9IgRqhsPBy74XiKGYydWQADBU=",
        "__NEXT_PREVIEW_MODE_ID": "08d92ceef4ba6772862f6f21e7430088",
        "__NEXT_PREVIEW_MODE_ENCRYPTION_KEY": "62f08cf4316fa086b42533872e147721c67e7c0ff854a25bfcda9de008023f1f",
        "__NEXT_PREVIEW_MODE_SIGNING_KEY": "61f2eec40696c9bd7171fbc2013b5a78fed9938b3e282bfb4ba6b537e281f9d3"
      }
    }
  },
  "instrumentation": null,
  "functions": {}
}